CHANGES.rst
LICENSE.txt
MANIFEST.in
README.rst
buildout.cfg
setup.cfg
setup.py
Products/__init__.py
Products.BeakerSessionDataManager.egg-info/PKG-INFO
Products.BeakerSessionDataManager.egg-info/SOURCES.txt
Products.BeakerSessionDataManager.egg-info/dependency_links.txt
Products.BeakerSessionDataManager.egg-info/namespace_packages.txt
Products.BeakerSessionDataManager.egg-info/not-zip-safe
Products.BeakerSessionDataManager.egg-info/requires.txt
Products.BeakerSessionDataManager.egg-info/top_level.txt
Products/BeakerSessionDataManager/__init__.py
Products/BeakerSessionDataManager/configure.zcml
Products/BeakerSessionDataManager/interfaces.py
Products/BeakerSessionDataManager/sessiondata.py
Products/BeakerSessionDataManager/tests/__init__.py
Products/BeakerSessionDataManager/tests/test_sessiondata.py
Products/BeakerSessionDataManager/www/add_sdm.pt
Products/BeakerSessionDataManager/www/sdm.gif