Metadata-Version: 2.1
Name: Products.BeakerSessionDataManager
Version: 2.1
Summary: Zope2 session implementation using Beaker
Home-page: http://github.com/davisagli/Products.BeakerSessionDataManager
Author: David Glick, Groundwire
Author-email: davidglick@groundwire.org
License: MIT
Keywords: zope sessions beaker
Platform: UNKNOWN
Classifier: Programming Language :: Python
Classifier: Programming Language :: Python :: 3.6
Classifier: Programming Language :: Python :: 3.7
Classifier: Framework :: Zope :: 4
Classifier: License :: OSI Approved :: MIT License
Provides-Extra: test
